linkaudit/__init__.py
linkaudit/_version.py
linkaudit/html_result.py
linkaudit/linkaudit.py
linkaudit/markdownhelpers.py
linkaudit/nocxhelpers.py
linkaudit-0.9.8.dist-info/METADATA
linkaudit-0.9.8.dist-info/WHEEL
linkaudit-0.9.8.dist-info/entry_points.txt
linkaudit-0.9.8.dist-info/licenses/LICENSE.md
linkaudit-0.9.8.dist-info/RECORD
