Metadata-Version: 2.4
Name: linkaudit
Version: 0.9.8
Summary: Checks broken URLs in markdown files.
Project-URL: Documentation, https://github.com/nocomplexity/linkaudit#readme
Project-URL: Issues, https://github.com/nocomplexity/linkaudit/issues
Project-URL: Source, https://github.com/nocomplexity/linkaudit
Author-email: Maikel Mardjan <mike@bm-support.org>
License-Expression: GPL-3.0-or-later
License-File: LICENSE.md
Classifier: Development Status :: 4 - Beta
Classifier: Programming Language :: Python
Classifier: Programming Language :: Python :: 3.12
Classifier: Programming Language :: Python :: 3.13
Classifier: Programming Language :: Python :: 3.14
Requires-Python: >=3.11
Requires-Dist: fire>=0.7.0
